odoo/addons/auth_oauth_ropc/README.rst
odoo/addons/auth_oauth_ropc/__init__.py
odoo/addons/auth_oauth_ropc/__manifest__.py
odoo/addons/auth_oauth_ropc/i18n/auth_oauth_ropc.pot
odoo/addons/auth_oauth_ropc/i18n/it.po
odoo/addons/auth_oauth_ropc/models/__init__.py
odoo/addons/auth_oauth_ropc/models/oauth_ropc_provider.py
odoo/addons/auth_oauth_ropc/models/res_users.py
odoo/addons/auth_oauth_ropc/readme/CONFIGURE.rst
odoo/addons/auth_oauth_ropc/readme/CONTRIBUTORS.rst
odoo/addons/auth_oauth_ropc/readme/DESCRIPTION.rst
odoo/addons/auth_oauth_ropc/readme/USAGE.rst
odoo/addons/auth_oauth_ropc/security/oauth_ropc_provider.xml
odoo/addons/auth_oauth_ropc/static/description/configuration.png
odoo/addons/auth_oauth_ropc/static/description/icon.png
odoo/addons/auth_oauth_ropc/static/description/index.html
odoo/addons/auth_oauth_ropc/views/oauth_ropc_provider.xml
odoo_addon_auth_oauth_ropc-16.0.1.0.0.10.dist-info/METADATA
odoo_addon_auth_oauth_ropc-16.0.1.0.0.10.dist-info/WHEEL
odoo_addon_auth_oauth_ropc-16.0.1.0.0.10.dist-info/top_level.txt
odoo_addon_auth_oauth_ropc-16.0.1.0.0.10.dist-info/RECORD
